asantiya/__init__.py
asantiya/__main__.py
asantiya/cli.py
asantiya/docker_manager.py
asantiya/logger.py
asantiya/ssh_manager.py
asantiya/accessories/__init__.py
asantiya/accessories/down.py
asantiya/accessories/logs.py
asantiya/accessories/ls.py
asantiya/accessories/reboot.py
asantiya/accessories/restart.py
asantiya/accessories/up.py
asantiya/app/__init__.py
asantiya/app/remove.py
asantiya/app/start.py
asantiya/app/stop.py
asantiya/schemas/__init__.py
asantiya/schemas/models.py
asantiya/utils/config.py
asantiya/utils/docker.py
asantiya/utils/load_env.py
asantiya/utils/misc.py
asantiya-0.1.5.dist-info/METADATA
asantiya-0.1.5.dist-info/WHEEL
asantiya-0.1.5.dist-info/entry_points.txt
asantiya-0.1.5.dist-info/licenses/LICENSE
asantiya-0.1.5.dist-info/RECORD
