Metadata-Version: 2.4
Name: asantiya
Version: 0.1.5
Summary: Docker deployment CLI tool for local and remote environments
Project-URL: Homepage, https://github.com/shahid-0/asantiya
Project-URL: Documentation, https://github.com/shahid-0/asantiya#readme
Project-URL: Issues, https://github.com/shahid-0/asantiya/issues
Author-email: Shahid Khan <shahiddev91@gmail.com>
License: MIT License
License-File: LICENSE
Keywords: cli,deployment,devops,docker
Classifier: Development Status :: 3 - Alpha
Classifier: Intended Audience :: Developers
Classifier: Intended Audience :: System Administrators
Classifier: License :: OSI Approved :: MIT License
Classifier: Programming Language :: Python :: 3.9
Classifier: Programming Language :: Python :: 3.10
Classifier: Programming Language :: Python :: 3.11
Classifier: Programming Language :: Python :: 3.12
Classifier: Programming Language :: Python :: 3.13
Classifier: Topic :: Software Development :: Build Tools
Classifier: Topic :: System :: Systems Administration
Classifier: Topic :: Utilities
Requires-Python: >=3.9
Requires-Dist: docker>=7.1.0
Requires-Dist: paramiko>=3.5.1
Requires-Dist: pydantic>=2.11.7
Requires-Dist: python-dateutil>=2.9.0
Requires-Dist: python-dotenv>=1.1.0
Requires-Dist: pyyaml>=6.0.2
Requires-Dist: tabulate>=0.9.0
Requires-Dist: typer>=0.16.0
Provides-Extra: dev
Requires-Dist: black>=23.0; extra == 'dev'
Requires-Dist: flake8>=6.0; extra == 'dev'
Requires-Dist: ipython>=8.0; extra == 'dev'
Requires-Dist: isort>=5.12; extra == 'dev'
Requires-Dist: mypy>=1.0; extra == 'dev'
Requires-Dist: pytest-cov>=4.0; extra == 'dev'
Requires-Dist: pytest>=7.0; extra == 'dev'
Requires-Dist: twine>=4.0; extra == 'dev'
Requires-Dist: types-paramiko>=3.0; extra == 'dev'
Requires-Dist: types-python-dateutil>=2.8; extra == 'dev'
Requires-Dist: types-pyyaml>=6.0; extra == 'dev'
Requires-Dist: types-tabulate>=0.9; extra == 'dev'
